{"CardID": "BUS0000006_User_table1A_01", "applicationID": "BUS0000006", "filters": {}, "fieldList": "ID Name DateOfComplaint Status", "sortBy": "ID", "limit": 5, "Type": "table1A", "header": {"title": "Employee Complaint", "subTitle": "My Development", "status": {"text": "User"}}, "columns": [{"title": "ID", "value": "{ID}"}, {"title": "Name", "value": "{Name}"}, {"title": "DateOfComplaint", "value": "{DateOfComplaint}"}, {"title": "Status", "value": "{Status}", "state": "{statusState}"}], "json": []}