{"Identification": {"Object": "COUNCIL036", "PartnerNo": "SmartPhone"}, "ApplicationControls": {"CreateNewItems": false, "CreateNewFields": [{"Field": "ID", "Attr": {"Attribute": "D"}}, {"Field": "ApplicantName", "Attr": {"Attribute": "E"}}, {"Field": "ContactNo", "Attr": {"Attribute": "E"}}, {"Field": "Email", "Attr": {"Attribute": "E"}}, {"Field": "Address", "Attr": {"Attribute": "E"}}, {"Field": "Postcode", "Attr": {"Attribute": "E"}}, {"Field": "ParticipantLastName", "Attr": {"Attribute": "E"}}, {"Field": "ParticipantFirstName", "Attr": {"Attribute": "E"}}, {"Field": "BirthDate", "Attr": {"Attribute": "E"}}, {"Field": "ParticipantGender", "Attr": {"Attribute": "E"}}, {"Field": "PreferredStartDate", "Attr": {"Attribute": "E"}}, {"Field": "PreferredDay", "Attr": {"Attribute": "E"}}, {"Field": "PreferredTime", "Attr": {"Attribute": "E"}}, {"Field": "PreferredCenter", "Attr": {"Attribute": "E"}}, {"Field": "Status", "Attr": {"Attribute": "E"}}, {"Field": "BookingFor", "Attr": {"Attribute": "E"}}, {"Field": "Q1", "Attr": {"Attribute": "D"}}, {"Field": "A1", "Attr": {"Attribute": "E"}}, {"Field": "Q2", "Attr": {"Attribute": "D"}}, {"Field": "A2", "Attr": {"Attribute": "E"}}, {"Field": "ApplicationDate", "Attr": {"Attribute": "E"}}, {"Field": "Approver", "Attr": {"Attribute": "E"}}], "PossibleValue": false, "PossibleValueFields": ["ParticipantGender", "Status", "PreferredTime", "PreferredCenter", "BookingFor", "A2"], "AttachmentFunction": true, "ServerUpdate": true, "ColorCoding": true, "ColorCodedFields": ["Status"], "ApplicationFilters": [], "ReadGeoCode": false, "GoogleMap": false, "GoogleMapTab": null, "MapFields": [], "SimpleValFileUpload": false, "CalculatedFieldsItem": [], "CalculatedFieldsHeaderItem": [], "CalculatedFieldsHeader": [], "RecordDownload": false, "CurrencySymbol": "", "BOTSetup": [], "FieldLabel": "SLabel", "PDFDownload": "", "ViewDesktopType": "", "ConfirmationEmail": "", "FileUpload": "", "DupChkUpload": []}, "ListScreenControls": [{"Action": {"name": "Reply", "flag": "Hide", "theme": "Emphasized", "linkField": "Status", "value": "Replied", "label": "Reply"}, "PopField": [{"change": {"change": "Append"}, "Field": "Question_Response"}]}, {"Action": {"name": "Process Booking", "flag": "Hide", "theme": "Default", "linkField": "ProcessingLog", "value": "Logged", "label": "Process Booking"}, "PopField": [{"change": {"change": "Append"}, "Field": "ProcessingLog"}]}], "Filters": {"Sorting": {"DataField": ["ID", "ApplicantName", "ApplicationDate", "Email", "ParticipantLastName", "ParticipantFirstName", "BirthDate", "ParticipantGender", "PreferredStartDate", "PreferredDay", "PreferredTime", "PreferredCenter", "Status"]}, "DateFilter": {"DataField": "ApplicationDate", "Sequence": "2", "Options": ["In Last 1 day", "In Last 3 day", "In Last 7 day", "In Last 15 day", "In Last 30 day"]}, "DataFilter": []}, "Graph": {"Dimension": [{"DropDownValue": "PreferredCenter", "Title": "Analysis based on Document Location"}, {"DropDownValue": "PreferredCenter", "Title": "Analysis based on Document Location"}], "KeyFigures": [{"DropDownValue": "Number of Record", "Action": "Count", "DataField": "ID", "SLabel": "Identification"}, {"DropDownValue": "Number of Record", "Action": "Count", "DataField": "ID", "SLabel": "Identification"}, {"DropDownValue": "Number of Record", "Action": "Count", "DataField": "ID", "SLabel": "Identification"}, {"DropDownValue": "Number of Record", "Action": "Count", "DataField": "ID", "SLabel": "Identification"}]}, "DetailPageControl": {"DetailPageTab": "Active", "TabDetails": [[{"value": "Tab1", "name": "Participant Details", "type": "Field", "fioriicon": "notes", "download": "Yes"}, {"value": "Tab2", "name": "Applicant Details", "type": "Field", "fioriicon": "citizen-connect", "download": "Yes"}, {"value": "Tab3", "name": "Additional Info", "fioriicon": "hint", "type": "Field", "download": "Yes"}, {"value": "Tab4", "name": "Chat", "fioriicon": "comment", "type": "Chat", "download": "Yes"}, {"value": "Tab5", "name": "Processing Log", "fioriicon": "comment", "type": "Chat", "download": "Yes"}, {"value": "Tab1", "name": "Participant Details", "type": "Field", "fioriicon": "notes", "download": "Yes"}, {"value": "Tab2", "name": "Applicant Details", "type": "Field", "fioriicon": "citizen-connect", "download": "Yes"}, {"value": "Tab3", "name": "Additional Info", "fioriicon": "hint", "type": "Field", "download": "Yes"}, {"value": "Tab4", "name": "Chat", "fioriicon": "comment", "type": "Chat", "download": "Yes"}, {"value": "Tab5", "name": "Processing Log", "fioriicon": "comment", "type": "Chat", "download": "Yes"}]]}, "Title": {"ApplicationTitle": "Book Lessons", "DetailTitle": "Book for Lessons"}, "FieldDefinition": {"FieldDefinition": [{"name": "ID", "type": "string", "width": "20", "Option": "", "SLabel": "Identification", "LLabel": "", "Currency": "No"}, {"name": "ApplicantName", "type": "string", "width": "50", "Option": "", "SLabel": "Applicant Name", "LLabel": "ApplicantName", "Currency": "No"}, {"name": "ContactNo", "type": "string", "width": "50", "Option": "", "SLabel": "Contact No", "LLabel": "ContactNo", "Currency": "No"}, {"name": "Email", "type": "string", "width": "50", "Option": "", "SLabel": "Email", "LLabel": "Email", "Currency": "No"}, {"name": "Address", "type": "string", "width": "200", "Option": "", "SLabel": "Address", "LLabel": "Address", "Currency": "No"}, {"name": "Postcode", "type": "string", "width": "20", "Option": "", "SLabel": "Postcode", "LLabel": "Postcode", "Currency": "No"}, {"name": "ParticipantLastName", "type": "string", "width": "50", "Option": "", "SLabel": "Participant Last Name", "LLabel": "", "Currency": "No"}, {"name": "ParticipantFirstName", "type": "string", "width": "50", "Option": "", "SLabel": "Participant First Name", "LLabel": "", "Currency": "No"}, {"name": "BirthDate", "type": "string", "width": "20", "Option": "", "SLabel": "Age", "LLabel": "Age", "Currency": "No"}, {"name": "ParticipantGender", "type": "string", "width": "10", "Option": "", "SLabel": "Participant Gender", "LLabel": "", "Currency": "No"}, {"name": "PreferredStartDate", "type": "Date", "width": "10", "Option": "", "SLabel": "Preferred Start Date", "LLabel": "", "Currency": "No"}, {"name": "PreferredDay", "type": "string", "width": "50", "Option": "", "SLabel": "Preferred Day", "LLabel": "", "Currency": "No"}, {"name": "PreferredTime", "type": "string", "width": "100", "Option": "", "SLabel": "Preferred Time", "LLabel": "PreferredTime", "Currency": "No"}, {"name": "PreferredCenter", "type": "string", "width": "200", "Option": "", "SLabel": "Preferred Center", "LLabel": "", "Currency": "No"}, {"name": "Status", "type": "string", "width": "20", "Option": "", "SLabel": "Status", "LLabel": "", "Currency": "No"}, {"name": "BookingFor", "type": "string", "width": "200", "Option": "mandatory", "SLabel": "You are booking for", "LLabel": "You are booking for", "Currency": "No"}, {"name": "Q1", "type": "string", "width": "200", "Option": "", "SLabel": "Question 1", "LLabel": "Q", "Currency": "No"}, {"name": "A1", "type": "string", "width": "500", "Option": "", "SLabel": "Answer 1", "LLabel": "A", "Currency": "No"}, {"name": "Q2", "type": "string", "width": "200", "Option": "", "SLabel": "Question 2", "LLabel": "Q", "Currency": "No"}, {"name": "A2", "type": "string", "width": "100", "Option": "", "SLabel": "Answer 2", "LLabel": "A", "Currency": "No"}, {"name": "ApplicationDate", "type": "Date", "width": "10", "Option": "", "SLabel": "Application Date", "LLabel": "ApplicationDate", "Currency": "No"}, {"name": "Approver", "type": "string", "width": "100", "Option": "", "SLabel": "Approver", "LLabel": "Approver", "Currency": "No"}, {"name": "ProcessingLog", "type": "string", "width": "500", "Option": "", "SLabel": "Processing Log", "LLabel": "Processing Log", "Currency": "No"}, {"name": "Question_Response", "type": "string", "width": "500", "Option": "", "SLabel": "Here Is Chat Details", "LLabel": "Question_Response", "Currency": "No"}]}, "ListField": {"ListField": [{"name": "ID", "ListField": "Display", "Sequence": "1", "grp": "Title"}, {"name": "ParticipantFirstName", "ListField": "Display", "Sequence": "1", "grp": "Title"}, {"name": "ParticipantLastName", "ListField": "Display", "Sequence": "1", "grp": "Title"}, {"name": "ParticipantGender", "ListField": "Display", "Sequence": "1", "grp": "Description"}, {"name": "BookingFor", "ListField": "Display", "Sequence": "1", "grp": "Description"}, {"name": "Status", "ListField": "Display", "Sequence": "1", "grp": "SubTitle"}, {"name": "ApplicationDate", "ListField": "Display", "Sequence": "1", "grp": "SubTitle"}]}, "DetailScreen": {"DetailScreen": [{"name": "ID", "Tab": "None", "Sequence": "1", "Mode": "Display"}, {"name": "ApplicantName", "Tab": "Tab2", "Sequence": "1", "Mode": "Edit"}, {"name": "ContactNo", "Tab": "Tab2", "Sequence": "1", "Mode": "Edit"}, {"name": "Email", "Tab": "Tab2", "Sequence": "1", "Mode": "Edit"}, {"name": "Address", "Tab": "Tab2", "Sequence": "1", "Mode": "Edit"}, {"name": "Postcode", "Tab": "Tab2", "Sequence": "1", "Mode": "Edit"}, {"name": "ParticipantLastName", "Tab": "Tab1", "Sequence": "1", "Mode": "Edit"}, {"name": "ParticipantFirstName", "Tab": "Tab1", "Sequence": "1", "Mode": "Edit"}, {"name": "BirthDate", "Tab": "Tab1", "Sequence": "1", "Mode": "Edit"}, {"name": "ParticipantGender", "Tab": "Tab1", "Sequence": "1", "Mode": "Edit"}, {"name": "PreferredStartDate", "Tab": "Tab3", "Sequence": "1", "Mode": "Edit"}, {"name": "PreferredDay", "Tab": "Tab3", "Sequence": "1", "Mode": "Edit"}, {"name": "PreferredTime", "Tab": "Tab3", "Sequence": "1", "Mode": "Edit"}, {"name": "PreferredCenter", "Tab": "Tab3", "Sequence": "1", "Mode": "Edit"}, {"name": "Status", "Tab": "None", "Sequence": "1", "Mode": "Edit"}, {"name": "BookingFor", "Tab": "None", "Sequence": "1", "Mode": "Edit"}, {"name": "Q1", "Tab": "Tab1", "Sequence": "1", "Mode": "Display"}, {"name": "A1", "Tab": "Tab1", "Sequence": "1", "Mode": "Edit"}, {"name": "Q2", "Tab": "Tab1", "Sequence": "1", "Mode": "Display"}, {"name": "A2", "Tab": "Tab1", "Sequence": "1", "Mode": "Edit"}, {"name": "ApplicationDate", "Tab": "None", "Sequence": "1", "Mode": "Edit"}, {"name": "Question_Response", "Tab": "Tab4", "Sequence": "1", "Mode": "Edit"}, {"name": "ProcessingLog", "Tab": "Tab5", "Sequence": "1", "Mode": "Display"}]}, "Item": [], "WizardStep": []}