{"Identification": {"Object": "EMP00002", "PartnerNo": "SmartPhone"}, "ApplicationControls": {"CreateNewItems": true, "CreateNewFields": [{"Field": "ID", "Attr": {"Attribute": "D"}}, {"Field": "EmployeeCode", "Attr": {"Attribute": "E"}}, {"Field": "EmployeeName", "Attr": {"Attribute": "E"}}, {"Field": "Currency", "Attr": {"Attribute": "E"}}, {"Field": "EntryDate", "Attr": {"Attribute": "E"}}, {"Field": "TravelDtFrom", "Attr": {"Attribute": "E"}}, {"Field": "TravelDateTo", "Attr": {"Attribute": "E"}}, {"Field": "ProjectCode", "Attr": {"Attribute": "E"}}, {"Field": "CostCentre", "Attr": {"Attribute": "E"}}, {"Field": "Location", "Attr": {"Attribute": "E"}}, {"Field": "TravelDetail", "Attr": {"Attribute": "E"}}, {"Field": "Status", "Attr": {"Attribute": "E"}}, {"Field": "TravelMode", "Attr": {"Attribute": "E"}}, {"Field": "Justification", "Attr": {"Attribute": "E"}}, {"Field": "Approver", "Attr": {"Attribute": "E"}}, {"Field": "FoodCost", "Attr": {"Attribute": "E"}}, {"Field": "TravelCost", "Attr": {"Attribute": "E"}}, {"Field": "StayCost", "Attr": {"Attribute": "E"}}, {"Field": "OtherCost", "Attr": {"Attribute": "E"}}], "PossibleValue": false, "PossibleValueFields": ["Currency", "ProjectCode", "CostCentre", "Status", "TravelMode"], "AttachmentFunction": false, "ServerUpdate": true, "ColorCoding": true, "ColorCodedFields": ["Status"], "ApplicationFilters": [], "ReadGeoCode": false, "GoogleMap": false, "GoogleMapTab": null, "MapFields": [], "SimpleValFileUpload": true, "CalculatedFieldsItem": [], "CalculatedFieldsHeaderItem": [], "CalculatedFieldsHeader": [], "RecordDownload": false, "CurrencySymbol": "\u00a3", "BOTSetup": [], "FieldLabel": "SLabel", "PDFDownload": "", "ViewDesktopType": false, "ConfirmationEmail": "", "FileUpload": "", "DupChkUpload": [], "CalculatedFields": {"Item": [], "HeaderItem": [], "Header": [{"CalculatedFormula": {"name": "Addition", "function": "ADD", "Target": "TotalAmount", "type": "Header"}, "Fields": [{"Source": "TravelCost", "Type": {"type": "Header"}}, {"Source": "StayCost", "Type": {"type": "Header"}}, {"Source": "OtherCost", "Type": {"type": "Header"}}, {"Source": "FoodCost", "Type": {"type": "Header"}}]}]}}, "ListScreenControls": [{"Action": {"name": "Reply", "flag": "Hide", "theme": "Default", "linkField": "Status", "value": "Response", "label": "Reply"}, "PopField": [{"change": {"change": "Append"}, "Field": "ProcessingLog"}]}], "Filters": {"Sorting": {"DataField": ["ID", "EmployeeName", "Status"]}, "DateFilter": {"DataField": "TravelDtFrom", "Sequence": "2", "Options": ["In Last 1 day", "In Last 3 day", "In Last 7 day", "In Last 15 day", "In Last 30 day"]}, "DataFilter": []}, "Graph": {"Dimension": [{"DropDownValue": "Location", "Title": "Analysis based on Document Location"}, {"DropDownValue": "Location", "Title": "Analysis based on Document Location"}, {"DropDownValue": "Location", "Title": "Analysis based on Document Location"}, {"DropDownValue": "Location", "Title": "Analysis based on Document Location"}, {"DropDownValue": "Location", "Title": "Analysis based on Document Location"}, {"DropDownValue": "Location", "Title": "Analysis based on Document Location"}], "KeyFigures": [{"DropDownValue": "Sum of TotalAmount", "Action": "Sum", "DataField": "TotalAmount", "SLabel": "Sum of Total Amount"}, {"DropDownValue": "Sum of TotalAmount", "Action": "Sum", "DataField": "TotalAmount", "SLabel": "Sum of Total Amount"}, {"DropDownValue": "Sum of TotalAmount", "Action": "Sum", "DataField": "TotalAmount", "SLabel": "Sum of Total Amount"}, {"DropDownValue": "Sum of TotalAmount", "Action": "Sum", "DataField": "TotalAmount", "SLabel": "Sum of Total Amount"}, {"DropDownValue": "Sum of TotalAmount", "Action": "Sum", "DataField": "TotalAmount", "SLabel": "Sum of Total Amount"}, {"DropDownValue": "Sum of TotalAmount", "Action": "Sum", "DataField": "TotalAmount", "SLabel": "Sum of Total Amount"}, {"DropDownValue": "Sum of TotalAmount", "Action": "Sum", "DataField": "TotalAmount", "SLabel": "Sum of Total Amount"}, {"DropDownValue": "Sum of TotalAmount", "Action": "Sum", "DataField": "TotalAmount", "SLabel": "Sum of Total Amount"}]}, "DetailPageControl": {"DetailPageTab": "Active", "TabDetails": [[{"value": "Tab1", "name": "Travel details", "type": "Field", "fioriicon": "request", "download": "Yes"}, {"value": "Tab2", "name": "Stay details", "type": "Field", "fioriicon": "database", "download": "Yes"}, {"value": "Tab3", "name": "Processing Log", "fioriicon": "step", "type": "Chat", "download": "Yes"}, {"value": "Tab4", "name": "Other Details", "fioriicon": "customer-view", "type": "Field", "download": "Yes"}, {"value": "Tab1", "name": "Travel details", "type": "Field", "fioriicon": "request", "download": "Yes"}, {"value": "Tab2", "name": "Stay details", "type": "Field", "fioriicon": "database", "download": "Yes"}, {"value": "Tab3", "name": "Processing Log", "fioriicon": "step", "type": "Chat", "download": "Yes"}, {"value": "Tab4", "name": "Other Details", "fioriicon": "customer-view", "type": "Field", "download": "Yes"}]]}, "Title": {"ApplicationTitle": "Travel Request", "DetailTitle": "Travel Request"}, "FieldDefinition": {"FieldDefinition": [{"name": "ID", "type": "string", "width": "20", "Option": "", "SLabel": "ID", "LLabel": "", "Currency": "No"}, {"name": "EmployeeCode", "type": "string", "width": "20", "Option": "", "SLabel": "Employee Code", "LLabel": "", "Currency": "No"}, {"name": "EmployeeName", "type": "string", "width": "50", "Option": "", "SLabel": "Employee Name", "LLabel": "", "Currency": "No"}, {"name": "TotalAmount", "type": "Num,2", "width": "20", "Option": "", "SLabel": "Total Amount", "LLabel": "", "Currency": "No"}, {"name": "Currency", "type": "string", "width": "5", "Option": "", "SLabel": "Currency", "LLabel": "", "Currency": "No"}, {"name": "EntryDate", "type": "Date", "width": "10", "Option": "", "SLabel": "Entry Date", "LLabel": "", "Currency": "No"}, {"name": "TravelDtFrom", "type": "Date", "width": "10", "Option": "", "SLabel": "Travel Date From", "LLabel": "", "Currency": "No"}, {"name": "TravelDateTo", "type": "Date", "width": "10", "Option": "", "SLabel": "Travel Date To", "LLabel": "", "Currency": "No"}, {"name": "ProjectCode", "type": "string", "width": "50", "Option": "mandatory", "SLabel": "Project Code", "LLabel": "", "Currency": "No"}, {"name": "CostCentre", "type": "string", "width": "50", "Option": "", "SLabel": "Cost Centre", "LLabel": "", "Currency": "No"}, {"name": "Location", "type": "string", "width": "50", "Option": "", "SLabel": "Location", "LLabel": "", "Currency": "No"}, {"name": "TravelDetail", "type": "string", "width": "500", "Option": "", "SLabel": "Travel Detail", "LLabel": "", "Currency": "No"}, {"name": "Justification", "type": "string", "width": "1000", "Option": "", "SLabel": "Justification", "LLabel": "", "Currency": "No"}, {"name": "Status", "type": "string", "width": "20", "Option": "", "SLabel": "Status", "LLabel": "", "Currency": "No"}, {"name": "TravelMode", "type": "string", "width": "50", "Option": "", "SLabel": "Travelling mode", "LLabel": "", "Currency": "No"}, {"name": "ProcessingLog", "type": "string", "width": "1000", "Option": "", "SLabel": "Processing Log", "LLabel": "Processing Log", "Currency": "No"}, {"name": "Approver", "type": "string", "width": "100", "Option": "", "SLabel": "Approver", "LLabel": "Approver", "Currency": "No"}, {"name": "FoodCost", "type": "Num,2", "width": "20", "Option": "", "SLabel": "Food Cost", "LLabel": "Food Cost", "Currency": "Yes"}, {"name": "TravelCost", "type": "Num,2", "width": "20", "Option": "", "SLabel": "Travel Cost", "LLabel": "Travel Cost", "Currency": "Yes"}, {"name": "StayCost", "type": "Num,2", "width": "20", "Option": "", "SLabel": "Stay Cost", "LLabel": "Stay Cost", "Currency": "Yes"}, {"name": "OtherCost", "type": "Num,2", "width": "20", "Option": "", "SLabel": "Other Cost", "LLabel": "Other Cost", "Currency": "No"}, {"name": "AdditionalInfo", "type": "string", "width": "500", "Option": "", "SLabel": "Additional Info", "LLabel": "Additional Info", "Currency": "No"}, {"name": "StayDetails", "type": "string", "width": "500", "Option": "", "SLabel": "Stay Details", "LLabel": "Stay Details", "Currency": "No"}]}, "ListField": {"ListField": [{"name": "ID", "ListField": "Display", "Sequence": "1", "grp": "Title"}, {"name": "EmployeeName", "ListField": "Display", "Sequence": "2", "grp": "SubTitle"}, {"name": "TotalAmount", "ListField": "Display", "Sequence": "1", "grp": "SubTitle"}, {"name": "Status", "ListField": "Display", "Sequence": "1", "grp": "SubTitle"}, {"name": "TravelDtFrom", "ListField": "Display", "Sequence": "1", "grp": "Description"}, {"name": "TravelDateTo", "ListField": "Display", "Sequence": "1", "grp": "Description"}, {"name": "Justification", "ListField": "Display", "Sequence": "1", "grp": "Description"}]}, "DetailScreen": {"DetailScreen": [{"name": "ID", "Tab": "None", "Sequence": "1", "Mode": "Display"}, {"name": "EmployeeCode", "Tab": "None", "Sequence": "2", "Mode": "Edit"}, {"name": "EmployeeName", "Tab": "None", "Sequence": "3", "Mode": "Edit"}, {"name": "EntryDate", "Tab": "None", "Sequence": "6", "Mode": "Edit"}, {"name": "TravelDtFrom", "Tab": "Tab1", "Sequence": "7", "Mode": "Edit"}, {"name": "TravelDateTo", "Tab": "Tab1", "Sequence": "8", "Mode": "Edit"}, {"name": "TravelDetail", "Tab": "Tab1", "Sequence": "12", "Mode": "Edit"}, {"name": "Justification", "Tab": "Tab1", "Sequence": "13", "Mode": "Edit"}, {"name": "Status", "Tab": "None", "Sequence": "32", "Mode": "Edit"}, {"name": "TravelMode", "Tab": "Tab1", "Sequence": "1", "Mode": "Edit"}, {"name": "TotalAmount", "Tab": "None", "Sequence": "1", "Mode": "Display"}, {"name": "TravelCost", "Tab": "Tab1", "Sequence": "1", "Mode": "Edit"}, {"name": "FoodCost", "Tab": "Tab2", "Sequence": "1", "Mode": "Edit"}, {"name": "StayCost", "Tab": "Tab2", "Sequence": "1", "Mode": "Edit"}, {"name": "OtherCost", "Tab": "Tab4", "Sequence": "1", "Mode": "Edit"}, {"name": "AdditionalInfo", "Tab": "Tab4", "Sequence": "1", "Mode": "Edit"}, {"name": "StayDetails", "Tab": "Tab2", "Sequence": "1", "Mode": "Edit"}, {"name": "ProcessingLog", "Tab": "Tab3", "Sequence": "1", "Mode": "Display"}, {"name": "CostCentre", "Tab": "Tab4", "Sequence": "1", "Mode": "Edit"}, {"name": "Approver", "Tab": "Tab4", "Sequence": "1", "Mode": "Edit"}, {"name": "Currency", "Tab": "Tab4", "Sequence": "1", "Mode": "Edit"}]}, "Item": [], "WizardStep": [{"id": "Step1", "name": "Request Details", "stepType": "FieldList", "intro": "Travel Request : Request Details", "fields": [{"name": "EmployeeCode", "Sequence": "1", "Mode": "Edit"}, {"name": "EmployeeName", "Sequence": "1", "Mode": "Edit"}, {"name": "Justification", "Sequence": "1", "Mode": "Edit"}]}, {"id": "Step4", "fields": [{"name": "TravelDtFrom", "Sequence": "1", "Mode": "Edit"}, {"name": "TravelDateTo", "Sequence": "1", "Mode": "Edit"}, {"name": "TravelMode", "Sequence": "1", "Mode": "Edit"}, {"name": "TravelDetail", "Sequence": "1", "Mode": "Edit"}, {"name": "Status", "Sequence": "1", "Mode": "Edit"}, {"name": "Approver", "Sequence": "1", "Mode": "Edit"}], "name": "Travel Details", "stepType": "FieldList", "intro": "Travel Request : Travel Details"}, {"id": "Step2", "fields": [{"name": "FoodCost", "Sequence": "1", "Mode": "Edit"}, {"name": "TravelCost", "Sequence": "1", "Mode": "Edit"}, {"name": "StayCost", "Sequence": "1", "Mode": "Edit"}, {"name": "OtherCost", "Sequence": "1", "Mode": "Edit"}], "name": "Travel Cost", "stepType": "FieldList", "intro": "Travel Cost Details"}]}