{
  "ItemNumber": {
    "type": "String",
    "required": [true, "Please add mandatory field :ItemNumber"],
    "maxlength": [20, "ID can not be more than 20 characters"]
  },
  "ID": {
    "type": "String",
    "required": [true, "Please add mandatory field :ID"],
    "maxlength": [20, "ID can not be more than 20 characters"]
  },
  "ItemDetails": {
    "type": "String",
    "required": [true, "Please add mandatory field :ItemDetails"],
    "maxlength": [100, "ItemDetails can not be more than 100 characters"]
  },
  "ItemQty": {
    "type": "String",
    "maxlength": [10, "InvQty can not be more than 10 characters"]
  },
  "ItemUOM": {
    "type": "String",
    "maxlength": [10, "InvUOM can not be more than 10 characters"]
  },
  "ItemPrice": {
    "type": "String",
    "maxlength": [10, "InvPrice can not be more than 10 characters"]
  },

  "ItemNetValue": {
    "type": "String",
    "maxlength": [20, "POItemNumber can not be more than 10 characters"]
  },

  "ItemVATRate": {
    "type": "String",
    "maxlength": [20, "ItemVATRate can not be more than 20 characters"]
  },
  "ItemVATVal": {
    "type": "String",
    "maxlength": [20, "InvVATRate can not be more than 10 characters"]
  },
  "ItemGrossVal": {
    "type": "String",
    "maxlength": [20, "ItemGrossVal can not be more than 20 characters"]
  },
  "ItemVATPer": {
    "type": "String",
    "maxlength": [10, "ItemVATPer can not be more than 10 characters"]
  },
  "SuppInvoiceNumber": {
    "type": "String",
    "maxlength": [10, "POQty can not be more than 10 characters"]
  },
  "InvQty": {
    "type": "String",
    "maxlength": [10, "POUOM can not be more than 10 characters"]
  },
  "InvPrice": {
    "type": "String",
    "maxlength": [10, "InvPrice can not be more than 10 characters"]
  },
  "InvVATRate": {
    "type": "String",
    "maxlength": [20, "InvVATRate can not be more than 20 characters"]
  },
  "InvNetValue": {
    "type": "String",
    "maxlength": [20, "InvNetValue can not be more than 10 characters"]
  },
  "InvVATVal": {
    "type": "String",
    "maxlength": [20, "InvVATVal can not be more than 20 characters"]
  },
  "InvGrossVal": {
    "type": "String",
    "maxlength": [20, "InvGrossVal can not be more than 20 characters"]
  },
  "ItemInvoiceStatus": {
    "type": "String",
    "maxlength": [10, "ItemInvoiceStatus can not be more than 10 characters"]
  },
  "InvCummQty": {
    "type": "String",
    "maxlength": [50, "InvCummQty can not be more than 10 characters"]
  },
  "BalanceInvQty": {
    "type": "String",
    "maxlength": [50, "BalanceInvQty can not be more than 10 characters"]
  },
  "PlannedShippingDate": {
    "type": "String",
    "maxlength": [50, "PlannedShippingDate can not be more than 10 characters"]
  },
  "ShippingDate": {
    "type": "String",
    "maxlength": [10, "ShippingDate can not be more than 10 characters"]
  },
  "DeliveryCompany": {
    "type": "String",
    "maxlength": [100, "DeliveryCompany can not be more than 100 characters"]
  },
  "TrackingNumber": {
    "type": "String",
    "maxlength": [50, "TrackingNumber can not be more than 50 characters"]
  },
  "TrackingWebsite": {
    "type": "String",
    "maxlength": [50, "TrackingWebsite can not be more than 50 characters"]
  },
  "ItemShippingStatus": {
    "type": "String",
    "maxlength": [50, "ItemInvoiceStatus can not be more than 50 characters"]
  },
  "InvVATPer": {
    "type": "String",
    "maxlength": [10, "InvVATPer can not be more than 10 characters"]
  }
}
