{
  "Title": {
    "ApplicationTitle": "OpenSAP Courses",
    "DetailTitle": "OpenSAP Course Details"
  },
  "Controls": {
    "USP": "UserProfile",
    "URL": "https://fierce-oasis-51455.herokuapp.com",
    "Source": {
      "SourceName": "jsonData",
      "SourceFile": "/NewConfig/openSAP_courses.json",
      "FieldMapping": [
        { "Teacher": "teacher" },
        { "StartDate": "start_date" },
        { "EndDate": "end_date" },
        { "Group": "Group" },
        { "SubGroup": "SubGroup" },
        { "Title": "title" },
        { "Overview": "abstract" },
        { "CourseLink": "url" },
        { "ReferenceID": "id" },
        { "ExternalStatus": "status" },
        { "Language": "language" },
        { "ExternalCode": "code" },
        { "Categories": "categories" },
        { "Image": "image" }
      ],
      "FixedValues": [
        { "External": "External" },
        { "Cost": "0.00" },
        { "Status": "Assigned" },
        { "Area": "SAP" },
        { "Duration": "Self Paced" },
        { "DateRequested": "@currentDate" },
        { "SelfAssign": "Yes" },
        { "Exam": "No" },
        { "Regulatory": "No" },
        { "Compliance": "No" },
        { "CreatedDate": "@currentDate" },
        { "Group": "ExternalCatalog" },
        { "SubGroup": "openSAP" },
        {
          "Terms": "I declare that I have read all the documents, viewed the videos and passed the test (if any) required for the completion of this training."
        }
      ]
    }
  },
  "ListFields": {
    "IntroField": "code",
    "TitleField": "title",
    "sStatus": "status",
    "fStatus": "Status",
    "numberField": "",
    "LFields": ["start_date", "end_date", "categories"]
  },
  "ListBOTFields": {
    "None": ["cardImage", "StatusState"],
    "Title": ["title", "status"],
    "SubTitle": ["code"],
    "Description": ["start_date", "end_date", "categories"]
  },
  "PossibleValues": ["Status"],
  "MButtons": [
    {
      "type": "DOWNLOAD",
      "name": "Download File",
      "icon": "sap-icon://download"
    },
    {
      "type": "APPHELP",
      "name": "Get App Help",
      "icon": "sap-icon://sys-help-2"
    },
    {
      "type": "BOT",
      "name": "Launch Assistant",
      "icon": "sap-icon://travel-request"
    },
    {
      "type": "VIEW",
      "name": "Change App View",
      "icon": "sap-icon://chart-table-view"
    },
    { "type": "ADD", "name": "Add Record", "icon": "sap-icon://add" },
    { "type": "UPLOAD", "name": "Upload Record", "icon": "sap-icon://upload" }
  ],
  "DButtons": [
    {
      "type": "ASSIGN",
      "name": "Assign Course",
      "icon": "sap-icon://share-2",
      "Dialog": "{label:'User',name:'user',type:'Email'}",
      "DialogSearch": "{URL}/api/v1/samrtApp/findUser/{user}",
      "URL": "util/assignCourseUser/TRAIN008/TRAIN007/{ReferenceID}/{user}",
      "Token": "Yes",
      "URLMethod": "POST"
    }
  ],
  "Tabs": [
    {
      "value": "Tab0",
      "name": "Cards",
      "type": "Cards",
      "fioriicon": "responsive"
    },
    {
      "value": "Tab1",
      "name": "CourseDetails",
      "fioriicon": "notes",
      "type": "FieldGroup"
    },
    {
      "value": "Tab4",
      "name": "CourseImages",
      "type": "carouselImage",
      "fioriicon": "picture"
    }
  ],
  "DetailFields": {
    "headerTitle": ["USP_Name"],
    "headerRole": ["USP_Role"],
    "headerImage": ["USP_Image"],
    "None": ["start_date", "end_date", "code", "Group", "SubGroup"],
    "Tab1": [
      {
        "GrpTitle": "Course Details",
        "Fields": ["title", "url", "abstract", "teacher"]
      },
      {
        "GrpTitle": "Other Details",
        "Fields": [
          "id",
          "code",
          "status",
          "language",
          "categories",
          "ReferenceID"
        ]
      }
    ],
    "Tab4": ["image"]
  },
  "ControlDisplay": {},
  "FieldDef": [
    {
      "name": "ID",
      "type": "string",
      "width": "20",
      "SLabel": "ID",
      "Option": "Optional"
    },
    {
      "name": "Group",
      "type": "string",
      "width": "100",
      "Option": "Optional",
      "SLabel": "Group",
      "LLabel": "Group"
    },
    {
      "name": "SubGroup",
      "type": "radiobutton",
      "width": "100",
      "Option": "Optional",
      "SLabel": "Sub Group",
      "LLabel": "Sub Group"
    },
    {
      "name": "title",
      "type": "string",
      "width": "50",
      "SLabel": "Course Title",
      "Option": ""
    },
    {
      "name": "url",
      "type": "string",
      "width": "1000",
      "SLabel": "Course URL",
      "Option": ""
    },
    {
      "name": "start_date",
      "type": "Date",
      "width": "1000",
      "SLabel": "Start Date",
      "Option": ""
    },
    {
      "name": "end_date",
      "type": "Date",
      "width": "1000",
      "SLabel": "End Date",
      "Option": ""
    },
    {
      "name": "teacher",
      "type": "string",
      "width": "1000",
      "SLabel": "Teacher",
      "Option": ""
    },
    {
      "name": "code",
      "type": "string",
      "width": "1000",
      "SLabel": "Course Code",
      "Option": ""
    },
    {
      "name": "abstract",
      "type": "string",
      "width": "1000",
      "SLabel": "Course Abstract",
      "Option": ""
    },

    {
      "name": "description",
      "type": "string",
      "width": "20",
      "SLabel": "Course Description",
      "Option": ""
    },
    {
      "name": "image",
      "type": "attachment",
      "width": "200",
      "SLabel": "Images",
      "Option": ""
    },
    {
      "name": "next_events",
      "type": "string",
      "width": "100",
      "SLabel": "Next Events",
      "Option": ""
    },
    {
      "name": "language",
      "type": "string",
      "width": "100",
      "SLabel": "Language",
      "Option": ""
    },
    {
      "name": "categories",
      "type": "string",
      "width": "100",
      "SLabel": "Categories",
      "Option": ""
    },
    {
      "name": "status",
      "type": "string",
      "width": "100",
      "SLabel": "status",
      "Option": ""
    },
    {
      "name": "Status",
      "type": "string",
      "width": "100",
      "SLabel": "Status",
      "Option": ""
    },
    {
      "name": "ReferenceID",
      "type": "string",
      "width": "100",
      "Option": "Optional",
      "SLabel": "Course ID",
      "LLabel": "Reference Course ID"
    },
    {
      "name": "Terms",
      "type": "string",
      "width": "200",
      "Option": "Optional",
      "SLabel": "Course ID",
      "LLabel": "Declaration"
    }
  ],
  "itemData": "No",
  "itemConfig": {
    "ItemFieldDefinition": [],
    "DisplayFields": [],
    "ItemButtons": {
      "itemDisplay": false,
      "itemAdd": false,
      "itemEdit": false,
      "itemDelete": false
    },
    "CreateFields": [],
    "ItemDetails": []
  },
  "CalculatedFields": {},
  "Create": "No",
  "Wizard": []
}
